gridio-1.0.5.dist-info/METADATA
gridio-1.0.5.dist-info/WHEEL
gridio.libs/libgcc_s-27e5a392.so.1
gridio/__init__.py
gridio/gridio.cpython-38-i386-linux-gnu.so
gridio/textgrid.py
gridio-1.0.5.dist-info/RECORD
