Metadata-Version: 2.4
Name: gridio
Version: 1.0.5
Classifier: Programming Language :: Rust
Classifier: Topic :: Scientific/Engineering
Classifier: Topic :: Text Processing
Requires-Dist: numpy
Summary: Rust-powered TextGrid parsing for Python with high performance APIs
Keywords: praat,textgrid,phonetics,linguistics,speech
Author-email: Chao Kong <kongchao1998@gmail.com>
Requires-Python: >=3.8
Project-URL: Homepage, https://github.com/fncokg/gridio
Project-URL: Documentation, https://fncokg.github.io/gridio/
Project-URL: Repository, https://github.com/fncokg/gridio
Project-URL: Issues, https://github.com/fncokg/gridio/issues
